speed_profiler/__init__.py
speed_profiler/speed_profiler.py
speed_profiler-0.0.4.dist-info/LICENSE
speed_profiler-0.0.4.dist-info/METADATA
speed_profiler-0.0.4.dist-info/WHEEL
speed_profiler-0.0.4.dist-info/top_level.txt
speed_profiler-0.0.4.dist-info/RECORD
