Metadata-Version: 2.1
Name: speed-profiler
Version: 0.0.4
Summary: Accurate speed profiler for Python code using perf_counter.
Home-page: https://github.com/TensorTom/speed-profiler
Author: TensorTom
License: MIT
Keywords: profiler,speed
Platform: UNKNOWN
Classifier: Development Status :: 4 - Beta
Classifier: Intended Audience :: Developers
Classifier: License :: OSI Approved :: MIT License
Classifier: Operating System :: OS Independent
Classifier: Programming Language :: Python
Classifier: Topic :: Software Development :: Libraries
Classifier: Topic :: Software Development :: Libraries :: Python Modules
